wakapi/__init__.py
wakapi/manual.py
wakapi/wakapi.py
wakapi-0.1.dist-info/LICENSE
wakapi-0.1.dist-info/METADATA
wakapi-0.1.dist-info/WHEEL
wakapi-0.1.dist-info/RECORD
